{"0": "add_reservation", "1": "affirm", "2": "book_number_room", "3": "book_room", "4": "bot_challenge", "5": "cleaning_time", "6": "delete_reservation", "7": "deny", "8": "edit_cleaning_room", "9": "edit_reservation", "10": "faq_breakfast_avail", "11": "faq_breakfast_time", "12": "faq_cancel_reservation", "13": "faq_cancellation_policy", "14": "faq_check_in_time", "15": "faq_check_out_time", "16": "faq_have_restaurant", "17": "faq_restaurant_time", "18": "get_number", "19": "goodbye", "20": "greet", "21": "help", "22": "schedule_room_cleaning", "23": "see_cleaning_schedule", "24": "show_reservation_id", "25": "show_rooms", "26": "start", "27": "stop", "28": "type_rooms"}